scoresheet_models/__init__.py
scoresheet_models/__init__.pyi
scoresheet_models/_contours.py
scoresheet_models/defs.py
scoresheet_models/drawing.py
scoresheet_models/fetch.py
scoresheet_models/model.py
scoresheet_models-0.3.1.dist-info/METADATA
scoresheet_models-0.3.1.dist-info/WHEEL
scoresheet_models-0.3.1.dist-info/top_level.txt
scoresheet_models-0.3.1.dist-info/RECORD
