Metadata-Version: 2.1
Name: scoresheet-models
Version: 0.3.1
Summary: Tools for storing, rendering and parsing chess scoresheet models
Author-email: Marcel Claramunt <marcel@moveread.com>
Project-URL: repo, https://github.com/moveread/scoresheet-models
Requires-Python: >=3.10
Requires-Dist: pydantic
Requires-Dist: python-kv[blob]
Requires-Dist: haskellian
